setup.py
ustciscrqin/__init__.py
ustciscrqin/ustciscrqin.py
ustciscrqin.egg-info/PKG-INFO
ustciscrqin.egg-info/SOURCES.txt
ustciscrqin.egg-info/dependency_links.txt
ustciscrqin.egg-info/requires.txt
ustciscrqin.egg-info/top_level.txt