Metadata-Version: 1.0
Name: ustciscrqin
Version: 2.2.4
Summary: This is ustciscrqin score package
Home-page: https://github.com/WolverineQin/ustciscr
Author: qjqqjq
Author-email: 1102692995@qq.com
License: MIT Licence
Keywords: pip,ustciscrqin,featureextraction
Platform: any
